{
  "objectInfo" : {
    "id" : "gMKmt4e0TSbgba602sNTmn",
    "name" : "m_param_04670257",
    "type" : "DTEMPLATE",
    "metadata" : {
      "modelVersion" : {
        "major" : 0,
        "minor" : 0
      },
      "repoInfo" : {
        "repoHandle" : "0110ZH170000000006ZE"
      },
      "contextAttributes" : [ {
        "name" : "id",
        "value" : "@1"
      } ],
      "additionalInfo" : {
        "description" : "Created for case 04670257 - testing param - assurance service",
        "contentType" : "JSON",
        "documentState" : "VALID"
      }
    }
  },
  "dataFileExtension" : "zip",
  "updateTime" : "2024-12-30T10:32:31.817Z",
  "objectRefs" : [ {
    "id" : "aIxzJmghWP3edbKa750bOQ",
    "name" : "SQL_Server_Sandy",
    "type" : "Connection",
    "metadata" : {
      "modelVersion" : {
        "major" : 0,
        "minor" : 0
      },
      "repoInfo" : {
        "repoHandle" : "0110ZH0B0000000001W9"
      },
      "contextAttributes" : null,
      "additionalInfo" : {
        "description" : null,
        "contentType" : "JSON",
        "documentState" : "COMPLETE"
      }
    },
    "path" : "/SYS"
  } ],
  "readableFileExtension" : null,
  "readableFilePresent" : false
}